tpu_inference_server/__init__.py
tpu_inference_server/__main__.py
tpu_inference_server/batch_worker.py
tpu_inference_server/cli.py
tpu_inference_server/client.py
tpu_inference_server/py.typed
tpu_inference_server/server.py
tpu_inference_server-0.1.1.dist-info/licenses/LICENSE
tpu_inference_server-0.1.1.dist-info/METADATA
tpu_inference_server-0.1.1.dist-info/WHEEL
tpu_inference_server-0.1.1.dist-info/entry_points.txt
tpu_inference_server-0.1.1.dist-info/top_level.txt
tpu_inference_server-0.1.1.dist-info/RECORD
