Metadata-Version: 2.4
Name: tpu-inference-server
Version: 0.1.1
Summary: A Flask-based inference server optimized for Google Cloud TPU v5e
Author: Vishwajeetsingh Desurkar
License: MIT
Project-URL: Homepage, https://github.com/yourusername/tpu-inference-server
Project-URL: Documentation, https://github.com/yourusername/tpu-inference-server#readme
Project-URL: Repository, https://github.com/yourusername/tpu-inference-server.git
Project-URL: Issues, https://github.com/yourusername/tpu-inference-server/issues
Keywords: tpu,inference,llm,machine-learning,google-cloud,pytorch,transformers,flask,openai-api
Classifier: Development Status :: 4 - Beta
Classifier: Intended Audience :: Developers
Classifier: Intended Audience :: Science/Research
Classifier: License :: OSI Approved :: MIT License
Classifier: Operating System :: OS Independent
Classifier: Programming Language :: Python :: 3
Classifier: Programming Language :: Python :: 3.9
Classifier: Programming Language :: Python :: 3.10
Classifier: Programming Language :: Python :: 3.11
Classifier: Topic :: Scientific/Engineering :: Artificial Intelligence
Requires-Python: >=3.9
License-File: LICENSE
Requires-Dist: flask>=2.0.0
Requires-Dist: pyyaml>=6.0
Requires-Dist: requests>=2.28.0
Requires-Dist: transformers>=4.30.0
Provides-Extra: dev
Requires-Dist: pytest>=7.0.0; extra == "dev"
Requires-Dist: pytest-cov>=4.0.0; extra == "dev"
Requires-Dist: black>=23.0.0; extra == "dev"
Requires-Dist: ruff>=0.1.0; extra == "dev"
Requires-Dist: mypy>=1.0.0; extra == "dev"
Dynamic: license-file
